{
  "code": "briqueteur",
  "code_provisoire": true,
  "noms": [
    "Briqueteur(euse)-maçon(ne)"
  ],
  "secteur": "batiment",
  "faits": [
    {
      "champ": "formation_requise",
      "valeur": "BRIQUETEUR-MAÇON ou Briqueteuse-maçonne DIPLÔME D’ÉTUDES PROFESSIONNELLES\r D.E.P. Va voir\r également la section « liens recommandés » à la fin de cette page \r (dont des vidéos de briqueteurs-maçons qui parlent de leur travail). EMPLOYEURS\r POTENTIELS : - Entreprises spécialisées en briquetage-maçonnerie - Entreprises de construction - Entreprises en rénovation -    Centres de rénovation -    Distributeurs de produits de maçonneries et matériaux de construction -    Fabricants de produits de maçonneries et matériaux de construction - À ton propre compte : , Rimouski (C.S.S. des Phares, région du Bas-Saint-Laurent) regarde la vidéo promotionnelle du programme, A.S.P. en lancement d'une entreprise également offerte au CFP Pavillon de l'Avenir , , Pavillon du Royaume, Saguenay (C.S.S. d e la Jonquière , région du Saguenay-Lac-Saint-Jean ) possibilité d'obtenir une bourse d'études de 1 5 00 $ accordée aux étudiants(es) québécois habitant à plus de 100 \r km du CFP remise par la C.S.S. de la Jonquière , regarde la vidéo \r promotionnelle du programme, A.S.P. en gestion d'une entreprise spécialisée de la construction également offerte ( à distance ) , , Trois-Rivières (C.S.S. \r Chemin-du-Roy , région de la Mauricie ) offert en enseignement individualisé ( selon ton rythme d'apprentissage ), regarde la vidéo \r promotionnelle du programme, regarde la vidéo \r des ateliers , A.S.P. en gestion d'une entreprise spécialisée de la construction également offerte , , \r Sherbrooke (C.S.S. Région-de-Sherbrooke , région de l'Estrie ) offert à temps complet sur 8 mois ou à temps partiel sur 15 mois , aussi offert en concomitance D.E.S./D.E.P . (permettant de compléter en même temps, les cours \r obligatoires de 4 e et/ou 5 e secondaire , voir la page suivante ) , regarde la vidéo \r promotionnelle du programme, A.S.P. en gestion d'une entreprise spécialisée de la construction également offerte au CFP de la Riveraine à Nicolet , (immeuble \r Asticou) , \r Gatineau (C.S.S. des Portages-de-l'Outaouais , région de l'Outaouais ) regarde la vidéo \r promotionnelle du programme, A.S.P. en lancement d'une entreprise également offerte au CFP Compétences Outaouais , anglais , regarde la vidéo \r promotionnelle du programme, A.S.P. en gestion d'une entreprise spécialisé de la construction également offerte au CFP Pierre-Dupuy , Mont-Tremblant (C.S.S. des Laurentides, région des Laurentides ) regarde la vidéo \r promotionnelle du programme, A.S.P. en gestion d'une entreprise spécialisée de la construction également offerte au CFP Construc Plus à Saint-Eustache , , Laval (C.S.S. de Laval , région de \r Laval ) offert en enseignement individualisé ( selon ton rythme d'apprentissage ), véritable chantier-école d oté d'ateliers et d'équipements et outillage à \r la fine pointe \r : atelier d'échafaudage, atelier de maçonnerie, atelier d'éléments \r décoratifs et préfabriqués, atelier de briquetage ), regarde la vidéo \r promotionnelle du programme, regarde la vidéo \r promotionnelle du centre, A.S.P. en gestion d'une entreprise spécialisée de la construction également offerte, , Longueuil (C.S.S. Marie-Victorin , région de la Montérégie ) offert en enseignement individualisé ( selon ton rythme d'apprentissage ), regarde la vidéo \r promotionnelle du programme, A.S.P. en gestion d'une entreprise spécialisée de la construction également offerte ,",
      "origine": {
        "source": "metiers_quebec",
        "date_captee": "2026-07-22",
        "methode": "scraping",
        "confiance": "moyenne"
      }
    },
    {
      "champ": "taches",
      "valeur": ": En tant\r que briqueteur-maçon ou briqueteuse-maçonne , tu seras responsable de \r tailler, scier, poser et de tirer les joints des pièces de maçonnerie comme les \r briques, de la pierre sciée, des blocs de verre, de la pierre de taille, des \r éléments architecturaux préfabriqués en béton à l’aide de m ortier, \r de ciment, de colles de construction, mousses ou tout autre adhésif à maçonnerie . Tu auras à ériger des murs,\r des cloisons, des fondations, des cheminées, des foyers, des fours, des égouts,\r des canalisations et autres structures semblables. Si tu te spécialises en restauration \r de la maçonnerie; tu auras également pour tâches de restaurer des ouvrages \r de maçonnerie par l 'étaiement, le démontage, le remontage, \r l'ancrage et le regréage des parements, la réfection des joints, le \r remodelage et la réfection des éléments de maçonnerie, le nettoyage et la \r protection des surfaces. Tu pourras travailler sur\r les chantiers de construction résidentielle, commerciale et institutionnelle,\r mais également sur les chantiers de construction industrielle et sur les\r chantiers de génie civil (fabriquer les murs à bordures des autoroutes\r notamment).",
      "origine": {
        "source": "metiers_quebec",
        "date_captee": "2026-07-22",
        "methode": "scraping",
        "confiance": "moyenne"
      }
    },
    {
      "champ": "qualites",
      "valeur": ": - Bonne condition physique car tu devras \r dans des conditions extérieures difficiles (chaleur) -    Aimer travailler à l'extérieur en toute saison -    Aisance dans le travail en hauteur -   Bonne force \r physique car tu auras à soulever des charges lourdes (briques, blocs de pierre, \r etc) - Bonnes habiletés et dextérité manuelles - Minutie, précision et souci du détail car tu auras à effectuer des\r travaux de précision - Aptitudes à travailler en équipe car tu auras à collaborer avec d’autres\r collègues ouvriers et techniciens sur le chantier PROFESSIONS\r APPARENTÉES : - Apprenti-briqueteur-maçon ou apprenti-briqueteuse-maçonne (en début de\r carrière) -    Conseiller(ère)-vendeur(euse) en produits de quincaillerie - Poseur( euse) de blocs de béton - Poseur( euse) de pierres -    Représentant(e) en produits de \r maçonneries et matériaux de construction - Technicien(ne) de\r construction (Forces canadiennes)",
      "origine": {
        "source": "metiers_quebec",
        "date_captee": "2026-07-22",
        "methode": "scraping",
        "confiance": "moyenne"
      }
    },
    {
      "champ": "exigences_admission",
      "valeur": ": - Polyvalence -    Mobilité un peu partout dans la province : - Soit détenir le D.E.S. - Soit avoir 16 ans et réussi les cours de français, anglais et\r mathématiques de 3 e secondaire ou leurs équivalents - Soit avoir 18 ans et posséder des connaissances équivalentes : - Subir un test de sélection d'aptitudes et de personnalité (CFP Le Chantier, CFP Quali-Tech) -    Se soumettre à un questionnaire écrit d'admission en ligne \r et une entrevue écrite en ligne (ÉMOICQ, disponible sur leur site web ) -    Se soumettre à un questionnaire écrit d'aptitudes et de \r mathématiques ( CFP Outaouais) : Aucun\r contingentement à ce programme Les candidats(es) répondant aux exigences \r d'admission et ayant réussi le test (s'il y a lieu) sont généralement admis. Qu'est-ce que la concomitance \r D.E.S./D.E.P. ? Qu'est-ce que l'e nseignement \r individualisé ? Est du\r Québec : - à temps complet de jour à l’automne . - à temps complet de jour à \r l'automne . Ouest du\r Québec : - à temps cmplet de jour \r à l' automne . - à temps complet (30 heures/sem sur 5 jours) de jour à l’automne , à temps partiel (18 heures/sem sur 3 jours) de jour à l’automne . - à temps complet de jour à l’automne . Région\r de Québec : - École des métiers et occupations de\r l’industrie de la construction ÉMOICQ (Pavillon principal ), Québec (C.S.S. de \r la Capitale) première \r école de la construction au Québec fondée en 1945 et seconde plus grande école de la construction du Québec , véritable chantier-école réparti sur 6 sites de formation pour plus de 2 000 étudiants(es) dans 12 \r métiers de la construction ( comprenant un atelier \r d'échafaudages, un atelier de maçonnerie, un atelier de conception d'éléments décoratifs ou préfabriqués en pierre et un atelier \r extérieur de briquetage, situés sur le \r site principal ); regarde la vidéo \r promotionnelle du programme, regarde la vidéo promotionnelle de l'École, A.S.P. en gestion d'une entreprise spécialisée de la construction également offerte , à temps \r complet de jour à l’automne . Région\r de Montréal : - Acess \r Career Centre , annexe Saint-Hubert (C.S.S. Riverside ) à temps complet de jour avec entrées continues tous \r les mois . programme exclusif en anglais au Québec - à temps complet de jour à l’automne . - à temps complet de jour avec \r entrées périodiques au cours de l'année scolaire . - à temps complet de jour avec entrées périodiques au cours de l'année scolaire . - École professionnelle de Saint-Hyacinthe , S ain t-Hyacinthe (C.S.S. de St-Hyacinthe , région de la Montérégie ) regarde la vidéo \r promotionnelle du programme, A.S.P. en gestion d'une entreprise spécialisée de la construction également offerte , à temps complet de \r jour à l'automne . - École des métiers de la\r construction de Montréal , Montréal - arrondissement Rosemont-La Petite \r Patrie (C.S.S. de Montréal , région de Montréal ) plus grande école de la construction du Québec , véritable chantier-école d'une superficie de 270 000 pi 2 regroupant des ateliers et installations pour plus de 2 000 étudiants(es) \r dans 1 6 métiers de la construction , \r dont : un atelier d'échafaudages, un atelier de \r maçonnerie, un atelier de conception d'éléments \r décoratifs ou préfabriqués en pierre et un atelier extérieur de briquetage ; regarde la vidéo promotionnelle du programme, regarde la vidéo \r promotionnelle de l'ASP; regarde la vidéo promotionnelle de l'école, A.S.P. en gestion d'une entreprise spécialisée de la construction également offerte , à temps complet de jour à l’automne et à l'hiver . LIENS\r RECOMMANDÉS : Tu veux avoir l'avis de \r briqueteurs-maçons sur leur métier ?, alors regar les \r vidéos suivants : la vidéo promotinnelle du métier réalisée par Compétences Québec ; les entrevues avec Jérémie et Alexandre ; \r étudiants en briquetage-maçonnerie au CFP Rimouski-Neigette et réalisées \r par la Commission scoalaire des Phares; l'entrevue avec William Caplette , étudiant en briquetage-maçonnerie au CFP \r Pierre-Dupuy de Longeuil et réalisée par la centre de services scolaires \r Marie-Victorin; les entrevues avec Julien Beaudin, Kevin Legros et Réjean Perron ; les premiers sont \r étudiants et le dernier est enseignant en briquetage-maçonnerie au CFP \r Le Chantier et réalisées par la centre de services scolaires de Laval; l'entrevue avec Gérard Breton ; briqueteur-maçon pour Maçonnerie Robin Goyette en \r Montérégie et réalisée par le Conseil provincial du Québec des métiers \r de la construction; l'entrevue avec Patrick Michaud , briqueteur-maçon spécialisé en restauration de \r maçonnerie et co-propriétaire de Michaud briques et pierres à Packington \r dans le Bas-St-Laurent et réalisée par TV Témis; l'entrevue avec Éric , briqueteur-maçon et propriétaire de SGV Construction de Laval \r et réalisée dans le cadre d'un projet pédagogique d'étudiants de la \r centre de services scolaires de Laval; les entrevues avec soldat Alex Gagnon et soldat Richard Desgagnés , le premier est \r technicien en construction  au 4 e escadron de génie construction à la 3 e Escadre de Bagotville au Québec de \r l'Aviation royale canadienne et le second est technicien en construction à la 4 e escadrille de génie construction de la 8 e Escadre Trenton en Ontario de l'Aviation \r royale canadienne et réalisées par les Forces canadiennes ; la vidéo sur \"les femmes dans les métiers de la construction \" réalisée par le CFP de \r la Baie-James; la vidéo sur \"les femmes dans les métiers de la construction \" réalisée par l'ÉMOICQ . liens divers : - Commission de construction du Québec : infos sur les carrières en construction, portrait de l'industrie, perspectives \r de carrières, certification et cartes de compétences, etc. - Conseil sectoriel canadien de la construction : portrait de l'industrie canadienne de la construction, infos sur les carrières \r et perspectives - Comité sectoriel de la main-d'oeuvre des \r industries des portes et fenêtres, du meuble et des armoires de cuisine",
      "origine": {
        "source": "metiers_quebec",
        "date_captee": "2026-07-22",
        "methode": "scraping",
        "confiance": "moyenne"
      }
    }
  ],
  "completude": {
    "description": false,
    "milieux_travail": false,
    "taches": true,
    "formation_requise": true,
    "qualites": true,
    "exigences_admission": true,
    "salaire_median": false
  }
}