{
  "code": "machiniste",
  "code_provisoire": true,
  "noms": [
    "Ajusteur - outilleur de machines"
  ],
  "secteur": "fabric_mec",
  "faits": [
    {
      "champ": "taches",
      "valeur": ": Si tu deviens un ou unemachiniste général(e); tu auras pour tâches de conduire et opérer des machines-outils conventionnelles (tour, scie motorisée, fraiseuse, rectifieuse, cisaille hydraulique, rouleau hydraulique, perceuse à colonne, presse plieuse, surfaceuse, machine de transfert, visseuse, etc.) afin d'usiner et de fabriquer des pièces mécaniques, simples ou complexes (en polymère, en plastique, en acier inoxydable ou tout autre type d’alliages spécialisés) servant à assembler, modifier ou réparer un véhicule, une machine, un appareil, un équipement ou tout autre produit en métal. Tu auras notamment à lire et interpréter les dessins et les devis; calculer les dimensions et les tolérances; mesurer et agencer les éléments à usiner; élaborer une gamme d’usinage approprié pour le type de pièce et son utilisation; monter la pièce sur la machine-outil; installer les gabarits et les outils de coupe; régler, faire fonctionner et entretenir diverses machines-outils conventionnelles; fabriquer et réparer des engrenages; ajuster et assembler les pièces métalliques usinées et les sous-assemblages au moyen d'outils manuels et mécaniques selon différents procédés; ainsi que vérifier, à l'aide d'instruments de mesure de précision, si les dimensions des produits sont exactes et conformes aux prescriptions. Plus la machine sera sophistiquée, plus la pièce fabriquée exigera de précision. Si tu deviens machiniste spécialisé(e) (aussi appelé \"machiniste de précision\"); tu auras pour tâches de conduire et opérer des machines-outils à commande numérique MOCN (tour à CN, fraiseuse à CN, aléseuse-perceuse, riveteuse, taraudeuse ou communément appelé \"centre d'usinage\") pour fabriquer des matrices servant à assembler des pièces complexes ou plus ou moins complexes de formes spécifiques ou particulières de haute précision selon les besoins et selon différents procédés. Tu auras notamment à d’interpréter des dessins complexes liés à l’usinage sur machines-outils; programmer et opérer des machines-outils à contrôle numérique utilisées dans les opérations de fraisage, de perçage, d’alésage, de taraudage, etc; monter les accessoires, les outils de coupe et la pièce à usiner; positionner en relation les coordonnées du système et de la pièce; ainsi que vérifier, à l'aide d'instruments de mesure de précision, si les dimensions des produits sont exactes et conformes aux prescriptions. Si tu deviens outilleur(euse)-ajusteur(euse); tu auras pour tâches d'opérer des machines d'outillage (tels que : rectifieuse plane, rectifieuse cylindrique, rectifieuse de profil, affûteuse, matrice, meule, etc.) afin de fabriquer et assembler des gabarits; assembler des matrices; fabriquer, assembler et faire la mise au point des calibres et des outils de coupe; assembler des composantes; réparer et modifier des outils de coupe ou d'assemblage ou des matrices; rectifier une pièce de formes irrégulières complexes sur une rectifieuse; usiner des pièces de haute précision par soudure (assemblage mécanosoudé); usiner des pièces de haute précision par électro-érosion, etc. On retrouve des machinistes dans presque toutes les types d'entreprises industrielles, autant les grandes industries que dans les PME, soit toutes celles où l'on retrouve des machines automatisées ou conventionnelles. Que ce soit une entreprise de haute technologie comme les manufacturiers d'aéronefs, les manufacturiers de camions, les manufacturiers d'appareils électroniques, les manufacturiers de systèmes de télécommunications, les fabricants d'équipements pour la production d'électricité ou les fabricants de structures métalliques, etc. On les retrouve aussi dans les industries alimentaires, les fabricants de meubles, les fabricants de produits en plastique ou caoutchouc, les industries papetières, les industries chimiques et pétrochimiques, les compagnies pharmaceutiques, les industries de première transformation des métaux (alumineries, aciéries, fonderies, etc.), au sein des compagnies minières, etc. Et bien sûr, les ateliers d'usinage; des entreprises spécialisées dans la fabrication de pièces sur mesure de toutes sortes pour la production unitaire ou la production en série afin de répondre aux besoins d'entreprises industrielles de tous les secteurs allant de de la construction d'infrastructures de génie civil comme les structures métalliques, les véhicules de transport (tels que les camions les autobus, etc.), des biomatériaux notamment pour les chirurgies dentaires ou l'orthopédie jusqu'à l'exigeante industrie aérospatiale. Ils sont généralement des sous-traitants de ces manufacturiers. QUALITÉS ET APTITUDESNÉCESSAIRES : -Avoir une bonne santé : ne pas avoir d'allergies, bonne résistance au bruit, à la chaleur et à la poussière -Avoir une bonne vision -Bonne perception des formes en 3D -Bonne condition et endurance physique car tu devras de longues heures debout ou dans des positions inconfortables -Intérêts pour la mécanique, les technologies et le milieu industriel -Facilité pour les calculs de mesures et la géométrie -Capacité de lire des plans et devis d'assemblage -Bonnes habiletés manuelles et dextérité manuelles car tu auras à utiliser et opérer divers types de machines-outils et manipuler -Minutie, précisionet souci du détail car tu devras fabriquer avec précision des petites pièces ou des pièces délicates et de grande qualité -Sens méthodique et capacité d'analyse car tu devras analyser et trouver rapidement une défectuosité ou une imperfection ou tout autre problème -Sens de l'observation et de l'initiativecar tu devras agir dès que tu détecteras une défectuosité à une machine -Sens des responsabilités car tu seras responsable du bon état de fonctionnement des machines-outils et de la qualité des pièces fabriquées ou usinées -Facilité à travailler en équipe et sous pression car tu auras à travailler en collaboration avec d'autres machinistes, des opérations de machines et équipements industriels, des mécaniciens industriels, des soudeurs, des électromécaniciens, des technologues et parfois, des ingénieurs -Connaissance de l’anglais car la documentation technique est généralement dans cette langue PROFESSIONS APPARENTÉES : - Ajusteur(euse) d'outils -Ajusteur(euse) de matrices (avec un A.S.P. en matriçage complété) - Aléseur(euse) de matrices -Conducteur(trice) de machines-outils à commandes numériques (avec un A.S.P. en usinage sur machines-outils à commandes numériques complété) -Contremaître ou contremaîtresse de machinistes (après quelques années d’expérience) - Finisseur(euse) de matrices - Finisseur(euse) de moules en métal - Forgeron ou forgeronne industriel - Fraiseur(euse) - Gabarieur(euse) -Machiniste de précision (avec un A.S.P. en usinage sur machines-outils à commandes numériques complété) - Machiniste spécialisé (avec un A.S.P. en usinage sur machines-outils à commandes numériques complété) -Machiniste-vérificateur(trice) (avec de l’expérience) -Machiniste-soudeur(e) (il faut compléter sa formation par un D.E.P. en soudage-montage) -Matriceur ou matriceuse (avec un A.S.P. en matriçage complété) - Mécanicien(ne)-ajusteur(euse) - Monteur ou monteuse de matrices (avec un A.S.P. en matriçage) - Monteur-mécanicien ou monteuse-mécanicienne - Mouleur(euse) de moules sur métal - Mouliste -Outilleur-matriceur ou outilleuse-matriceuse (avec A.S.P. en outillage ou matriçage complété) -Outilleur-ajusteur ou outilleuse-ajusteuse de gabarits (avec un A.S.P. en outillage complété) -Outilleur-rectifieur ou outilleuse-rectifieuse (avec un A.S.P. en outillage complété) -Outilleur ou outilleuse (avec un A.S.P. en outillage complété) - Outilleur ou outilleuse d'outils au carbure(avec un A.S.P. en outillage complété) - Outilleur ou outilleuse d'outils et de calibres (avec un A.S.P. en outillage complété) -Régleur-conducteur ou régleuse-conductrice de machines-outils à commande numérique (avec un A.S.P. en usinage sur machines-outils complété) -Régleur-conducteur ou régleuse-conductrice de perceuses -Régleur-conducteur ou régleuse-conductrice de rectifieuses -Régleur-conducteur ou régleuse-conductrice de tours - Réparateur(trice) d'outils - Réparateur(trice) de matrices - Traceur-mécanicien ou traceuse-mécanicienne - (Forces armées - Armée de terre) formation offerte par les Forces - (Forces armées - Force aérienne) formation offerte par les Forces - Usineur(euse) - Vérificateur(trice) d'usinage EMPLOYEURS POTENTIELS : • Ateliers d'usinage • Ateliers de fabrication d'outils de production • Cimenteries • Fabricants de machines-outils pour le travail du métal • Industries aérospatiales (assemblage d'aéronefs, assemblage de composants pour aéronefs tels que : trains d'atterrissage ou moteurs, assemblage de composants pour satellites, fabricants de pièces pour aéronefs, fabricants d'éléments ou garnitures intérieures pour aéronefs, etc.) • Industries agroalimentaires (laiteries, crèmeries, brasseurs, pâtes alimentaires, pâtisseries industrielles, boulangeries industrielles, transformation de viandes ou volailles, usines d'embouteillage, etc) • Industries chimiques et pétrochimiques (raffineries, produits ménagers, produits d’entretien, fertilisants, peinture et solvants, produits du tabac, produits chimiques industriels, etc) • Industries de fabrication d’équipements de mécanique du bâtiment (fournaises, génératrices, climatiseurs, chaufferettes, échangeurs d'air, ascenseurs, etc) • Industries de fabrication de produits de consommation (jouets, jeux, équipements pour parcs de jeux, outils de menuiserie, outils de jardinage etc) • Industries de fabrication de produits électriques (instruments scientifiques, appareils électriques domestiques, matériel de distribution électrique, matériel électrique industriel, etc) • Industries de fabrication de produits électroniques (appareils audiovidéo, ordinateurs, matériel de télécommunication, équipements électroniques industriels, instruments de navigation, etc) • Industries de fabrication de produits mécaniques (équipements industriels, machines, tracteurs, matériel agricole, matériel forestier, matériel minier, outils, matrices, poinçons, etc) • Industries de l'optique et de la photonique (instruments de précision, instruments de mesure, instruments de navigation, systèmes de lecture optique, systèmes de vision nocturne, fibres optiques pour les télécommunications, etc) • Industries de la plasturgie et du caoutchouc (pneus, emballages, pièces pour véhicules, revêtements de sols, jouets, articles ménagers, outils de jardinage, bacs, contenants ou sacs, meubles de jardin, produits pour le bâtiment, etc) • Industries de la transformation des produits du bois (panneaux structureaux, placages, contreplaqués, scieries, etc) • Industries du meuble et bois ouvré (meubles résidentiels, meubles de bureau, meubles commerciaux, portes et fenêtres, menuiserie architecturale, etc) • Industries des textiles et du vêtement (tissus, textiles industriels, vêtements de sport, vêtements de travail, vêtements pour dames, vêtements pour hommes, vêtement pour enfants, etc) • Industries du matériel de transport (automobiles, camions, autobus, embarcations nautiques, voitures de trains et métros, motoneiges, VTT, camions à déchets, camions à incendie, pièces pour automobiles, pièces pour véhicules lourds, pièces pour véhicules récréatifs, pièces pour embarcations nautiques, chantiers maritimes, etc.) • Industries du recyclage • Industries métallurgiques (alumineries, fonderies de métaux ferreux, fonderies de métaux non ferreux, aciéries, fabricants de structures, fabricants de divers produits en métal, etc) • Industries papetières (emballages, papiers de spécialité, papiers d'impression, papier hygiénique, papiers de sécurité, cartons, etc) • Industries pharmaceutiques et cosméceutiques (médicaments, vaccins, articles médicaux jetables, cosmétiques, produits de toilette, etc) • Imprimeries industrielles • centres de services scolaires, cégeps et universités • EXIGENCES DES EMPLOYEURS : - La plupart des employeurs font passer un test d'embauche - Horaires sur quarts (jour/soir/nuit) -Connaissance de l’anglais (certains exigent le bilinguisme) -Polyvalence -Capacité de s’adapter aux nombreux changements technologiques -Une formation complémentaire en soudage (ex : DEP en soudage-montage), augmentera de façon significative tes chances d’obtenir un emploi. PLACEMENT : Selon les données disponibles au 1er juin 2019 : Pour le D.E.P. en techniques d'usinage : Le placement estbon, 74 % des répondants(es) qui se sont dirigés vers le marché du travail ont obtenu un emploi relié à leurs études dont la presque totalitésont à temps complet. Quelques autres répondants(es), soit 21 % ont choisi de poursuivre leurs études soit au niveau du ASP, soit dans un DEP connexe (soudage, électromécanique, mécanique industrielle ou montage mécanique en aérospatial) ou au collégial en technologie du génie mécanique, en technologie du génie aérospatial ou en technologie du génie industriel (",
      "origine": {
        "source": "metiers_quebec",
        "date_captee": "2026-07-22",
        "methode": "scraping",
        "confiance": "moyenne"
      }
    },
    {
      "champ": "milieux_travail",
      "valeur": "d'une durée de 3 semaines. L'Attestation d'études collégiales en technologie des véhicules électriques A.E.C. a une durée totale de 525 heures à temps complet dont un projet intégrateur de 150 heures) offert au . Ce NOUVEAU programme estdestiné aux titulaires d'un DEP ou d'un AEC en électrotechnique ou en fabrication mécanique dont les diplômés(es) en techniques d'usinage. Il a former du personnel qualifié en conception et fabrication de véhicules électriques. Elle comporte les cours suivants : la profession de technicien en véhicules électriques, éléments mécaniques, DAO et outils informatiques, éléments électriques et électroniques, accumulateurs et recharge, motorisation électrique, contrôle de la qualité, stage en entretien de 3 semaines, ainsi qu'un projet intégrateur en véhicules électriques de 150 heures. Le Diplôme d'études professionnelles en soudage-montage D.E.P. a une durée totale de 1 800 heures, c'est-à-dire 2 ans à temps complet (de jour ou de soir selon les centres de formation). Il permet de combiner la formation de machiniste avec celle de la formation de soudeur qui est très recherchée par les employeurs, notamment dans les grandes industries du transport, les industries de l'électronique et de l'informatique, les industries métallurgiques, les manufacturiers d'équipements énergétiques, les industries pétrolières et certains ateliers d'usinage spécialisée. Pour plus de détails, consulte la page du métier de . Le Diplôme d’études professionnelles D.E.P. en tôlerie de précision - concentration en tôlerie aéronautique a une durée totale de 1 275 hres, c’est-à-dire 1½ an offert à temps complet. Il comporte des cours d'introduction au métier, mathématiques appliquées à la métallurgie, dessin de croquis, lecture et interprétation de plans, relevés et interprétation de mesures, matériaux et procédés, santé et sécurité au travail, production de pièces pliées, techniques de soudage par résistance, production de pièces roulées et embossées, techniques d'usinage manuel, production de pièces embouties et poinçonnées, programmation et réglage de machines de coupe et de façonnage, conduite et opération d'une poinçonneuse à commande numérique, production sérielle de pièces pliées et nouvelles organisations du travail, techniques de pose et retrait d'attaches et de rivets, correction de formes de pièces, production d'un sous-ensemble, ainsi qu'un stage en industrie aérospatiale d'une durée de 3 semaines. Pour plus de détails, consulte la page du métier de . Le Diplôme d’études professionnelles D.E.P. en tôlerie de précision - concentration en tôlerie industrielle a une durée totale de 1 275 hres, c’est-à-dire 1½ an offert à temps complet. Il comporte des cours d'introduction au métier, mathématiques appliquées à la métallurgie, dessin de croquis, lecture et interprétation de plans, relevés et interprétation de mesures, matériaux et procédés, santé et sécurité au travail, production de pièces pliées, techniques de soudage par résistance, production de pièces roulées et embossées, techniques d'usinage manuel, production de pièces embouties et poinçonnées, programmation et réglage de machines de coupe et de façonnage, conduite et opération d'une poinçonneuse à commande numérique, production sérielle de pièces pliées et nouvelles organisations du travail, conduite et opération d'une découpeuse au laser, techniques de pose d'attaches, production d'un assemblage, ainsi qu'un stage en industrie métallurgique ou du matériel de transport d'une durée de 3 semaines. Pour plus de détails, consulte la page du métier de . ÉTUDES SUPÉRIEURES : Tu pourras également poursuivre tes études au niveau collégial dans le cadre du D.E.C. en technologie du génie mécanique, du DEC en technologie de la construction aéronautique, du D.E.C. en technologie de la maintenance industrielle, du DEC en technologie du génie industriel, du D.E.C. en technologie du génie de la plasturgie ou du D.E.C. en technologie des matériaux composites. Par contre, tu devras avoir réussi certains cours préalables du secondaire pour y avoir accès. EXIGENCES D’ADMISSION : -Soit détenir le D.E.S. ou d'un D.E.P. -Soit avoir 16 ans au 30 septembre et avoir réussi les cours de français, anglais et mathématiques de 4e secondaire ou leurs équivalents -Soit avoiréussi les cours de français, anglais et mathématiques de 3e secondaire ou leurs équivalents ET poursuivra sa formation générale en concomitance avec sa formation professionnelle pour obtenir les unités de 4e secondaire qui lui manquent en langue d’enseignement, en langue seconde et en mathématiques -Soit avoir 18 ans et posséder des connaissances équivalentes AUTRE EXIGENCE D’ADMISSION : - Subir des tests de sélection en habiletés manuelles et/ou d'aptitudes et de personnalité (École des métiers de l'aérospatiale de Montréal, Centre d'études professionelles de St-Jérôme, Centre régional intégré de formation) Note : ces tests visent à évaluer tes habiletés manuelles, tes capacités à faire des mesures de précision et lire et comprendre des plans et devis d'assemblage, ta capacité à résoudre des problèmes, ainsi que le profil d'intérêts et de personnalité en lien avec le métier convoitéetc. Pour plus de détails, consulte le centre de formation. STATISTIQUES D’ADMISSION : Ce programme n’est pas contingenté Les candidats(es) répondant aux conditions d'admission sont généralement admis. ENDROIT DE FORMATION : Demande d’admission via Internet, consulte Qu'est-ce que l'? Qu'est-ce que l'e? Qu'est-ce que la ? Est et Nord du Québec (Bas-St-Laurent, Saguenay-Lac-St-Jean, Gaspésie-Iles, Abiti-Témiscamingue, Côte-Nord) : Côte-Nord : - , Baie-Comeau (C.S.S. de l'Estuaire) possibilité d'obtenir une bourse d'études de 1 700 $ de la Commission des partenaires du marché du travail (visant la promotion de cette carrière en région éloignée), offert en enseignement individualisé en classe, aussi offert en concomitance D.E.S./D.E.P (permettant de compléter en même temps, les cours obligatoires de 4e et/ou 5e secondaire), possibilité de compléter ta formation avec un D.E.P. en soudage-montage, offert au CFP de Sept-Îles, admissions ouvertes à temps complet de jour avec entrées périodiques au cours de l'année scolaire. Bas-St-Laurent et Gaspésie : - , Gaspé (C.S.S. des Chic-Chocs) possibilité d'obtenir une bourse d'études de 1700 $ de la Commission des partenaires du marché du travail (visant la promotion de cette carrière en région éloignée), offert en enseignement individualisé, possibilité de compléter ta formation avec un D.E.P. en soudage-montage, admissions à temps complet de jour à l'automne. - , campus de Matane (C.S.S. des Monts-et-des-Marées) offert en enseignement individualisé, possibilité de compléter ta formation avec un D.E.P. en soudage-montage ou avec un D.E.P. en mécanique industrielle (campus d'Amqui), regarde la (et le ) du programme; admissions à temps complet de jour avec entrées périodiques au cours de l'année scolaire. -, Rivière-du-Loup (C.S.S. Kamouraska-Rivière-du-Loup) offert en formule traditionnelle en classe et en atelier, regarde la du programme, possibilité de compléter ta formation avec un D.E.P. en soudage-montageou avec un D.E.P. en mécanique industrielle (offert au CFPRO à Amqui), admissions à temps complet de jour à l’automne. Saguenay et Lac-St-Jean : -, Alma (C.S.S. du Lac-St-Jean) possibilité d'obtenir unebourse d'études de 2 500 $ émise par la C.S.S.du Lac Saint-Jean et accordée à un(e) étudiant(e) de l'extérieur du Saguenay-Lac-Saint-Jean qui s'inscrit dans ce programme (voir la ), possibilité d'obtenir une bourse d'études de 1 700 $ de la Commission des partenaires du marché du travail (visant la promotion de cette carrière en région éloignée), offert en formule intensive sur 14 mois, offert en formule duale (50 % des apprentissages en classe et en atelier à l'école et 50 % de travaux pratiques et stages souvent rémunérés en entreprise) en collaboration avec des entreprises partenaires de la région, aussi offert en concomitance D.E.S./D.E.P. (permettant de compléter en même temps, les cours obligatoires de 4e et/ou 5e secondaire), regarde la du programme, possibilité de compléter ta formation avec un D.E.P. en soudage-montage ou avec un D.E.P. en mécanique industrielle (offert au CFP de Jonquière), admissionsà temps complet de jour à l'automne. Ouestet centre du Québec (Mauricie-Bois-Francs, Estrie, Centre-du-Québec, Outaouais) : Abitibi-Témiscamingue : - , Amos (C.S.S. Harricana) possibilité d'obtenir une bourse d'études de 1 700 $ de la Commission des partenaires du marché du travail (visant la promotion de cette carrière en région éloignée), possibilité d'obtenir une bourse d'études permettant d'offrir l’hébergement en résidence étudiante à tarif réduit aux étudiants(es) de l’extérieur de la MRC de l'Abitibi-Ouest voir la , offert en enseignement individualisé, possibilité de bénéficier d’une cédule flexible permettant la conciliation travail-famille ou la conciliation travail-études (possibilité aussi d'occuper un emploi à temps partiel en industrie), aussi offert en concomitance D.E.S./D.E.P. (permettant de compléter en même temps, les cours obligatoires de 4e et/ou 5e secondaire), regarde la du programme, admissions à temps complet (5 jrs/sem) OU à temps partiel (3 jrs/sem) de jour à l'automne et à l'hiver. Centre-du-Québec : - , Drummondville (C.S.S. des Chênes) offert en alternance travail-études, possibilité de compléter ta formation avec un D.E.P. en soudage-montage,",
      "origine": {
        "source": "metiers_quebec",
        "date_captee": "2026-07-22",
        "methode": "scraping",
        "confiance": "moyenne"
      }
    }
  ],
  "completude": {
    "description": false,
    "milieux_travail": true,
    "taches": true,
    "formation_requise": false,
    "qualites": false,
    "exigences_admission": false,
    "salaire_median": false
  }
}